codenav_python-0.0.2.dist-info/METADATA
codenav_python-0.0.2.dist-info/WHEEL
codenav/__init__.py
codenav/codenav.cp38-win32.pyd
codenav_python-0.0.2.dist-info/RECORD
