Metadata-Version: 2.3
Name: codenav-python
Version: 0.0.2
Classifier: Programming Language :: Rust
Classifier: Programming Language :: Python :: Implementation :: CPython
Classifier: Programming Language :: Python :: Implementation :: PyPy
Summary: Python bindings for CodeNav.
Author-email: RussellLuo <luopeng.he@gmail.com>
Requires-Python: >=3.8
Project-URL: repository, https://github.com/RussellLuo/codenav
